{
  "name": "CredentialType",
  "fields": [
    {
      "fieldName": "name",
      "fieldType": "String",
      "fieldValidateRules": ["required"]
    },
    {
      "fieldName": "identifier",
      "fieldType": "String",
      "fieldValidateRules": ["required"]
    },
    {
      "fieldName": "active",
      "fieldType": "Boolean"
    },
    {
      "fieldName": "createdBy",
      "fieldType": "String"
    },
    {
      "fieldName": "createdDate",
      "fieldType": "ZonedDateTime"
    },
    {
      "fieldName": "updatedBy",
      "fieldType": "String"
    },
    {
      "fieldName": "updatedDate",
      "fieldType": "ZonedDateTime"
    }
  ],
  "relationships": [],
  "changelogDate": "20200604150253",
  "entityTableName": "credential_type",
  "dto": "no",
  "pagination": "no",
  "service": "no",
  "jpaMetamodelFiltering": false,
  "fluentMethods": true,
  "readOnly": false,
  "embedded": false,
  "clientRootFolder": "",
  "applications": ["gadi"]
}
